ftsa/__init__.py
ftsa/cli/__init__.py
ftsa/cli/exceptions.py
ftsa/cli/main.py
ftsa/cli/modules/__init__.py
ftsa/cli/modules/init_parser.py
ftsa/cli/modules/install_upgrade_parser.py
ftsa/cli/modules/properties.py
ftsa/cli/modules/run_report_parser.py
ftsa/cli/projects/base_project/data/UC000-CT002-dados.csv
ftsa/cli/projects/base_project/features/UC000-Login/CT001-LoginRealizado.robot
ftsa/cli/projects/base_project/features/UC000-Login/CT002-LoginNaoRealizado.robot
ftsa/cli/projects/base_project/features/UC000-Login/CT003-PersonTableCRUDOracle.robot
ftsa/cli/projects/base_project/page_objects/LoginPage.robot
ftsa/cli/projects/base_project/resources/locators.py
ftsa/cli/projects/commons/.gitignore
ftsa/cli/projects/commons/Dockerfile
ftsa/cli/projects/commons/LICENSE
ftsa/cli/projects/commons/README.md
ftsa/cli/projects/commons/main.py
ftsa/cli/projects/commons/project.properties
ftsa/cli/projects/example_project/data/CT002-dados.csv
ftsa/cli/projects/example_project/data/CT003-dados.csv
ftsa/cli/projects/example_project/data/img/botao_login_novamente.png
ftsa/cli/projects/example_project/features/TesteMyLibCalculadora.robot
ftsa/cli/projects/example_project/features/UC000-AutenticacaoDoUsuario/CT001-AutenticacaoUsuarioSucesso.robot
ftsa/cli/projects/example_project/features/UC000-AutenticacaoDoUsuario/CT002-AutenticacaoUsuarioNaoRealizada.robot
ftsa/cli/projects/example_project/features/UC000-AutenticacaoDoUsuario/CT003-AutenticacaoUsuarioNaoRealizadaEmBranco.robot
ftsa/cli/projects/example_project/page_objects/AutenticacaoUsuarioPage.robot
ftsa/cli/projects/example_project/resources/MyLibCalculadora.py
ftsa/cli/projects/example_project/resources/locators.py
ftsa/cli/projects/services_project/data/ct01.json
ftsa/cli/projects/services_project/data/ct05.json
ftsa/cli/projects/services_project/data/default_user.json
ftsa/cli/projects/services_project/features/CT1_GET_Request.robot
ftsa/cli/projects/services_project/features/CT2_POST_Request.robot
ftsa_tjpb-2.6.1.dist-info/LICENSE
ftsa_tjpb-2.6.1.dist-info/METADATA
ftsa_tjpb-2.6.1.dist-info/WHEEL
ftsa_tjpb-2.6.1.dist-info/entry_points.txt
ftsa_tjpb-2.6.1.dist-info/top_level.txt
ftsa_tjpb-2.6.1.dist-info/RECORD
