Metadata-Version: 2.1
Name: ftsa-tjpb
Version: 2.6.1
Summary: Framework de Teste de Sistemas Automatizado
Home-page: http://gitlab.tjpb.jus.br/testes/ftsa-tjpb.git
Author: Carlos Diego Quirino Lima
Author-email: diegoquirino@gmail.com
License: UNKNOWN
Keywords: ftsa framework teste sistemas automatizado tjpb
Platform: windows linux
Classifier: Programming Language :: Python :: 3
Classifier: License :: OSI Approved :: MIT License
Classifier: Operating System :: OS Independent
Requires-Python: >=3.6
License-File: LICENSE
Requires-Dist: docker
Requires-Dist: setuptools
Requires-Dist: wheel
Requires-Dist: twine
